lens/__init__.py
lens/model.py
lens/utils.py
llm_lens-0.0.0.3.dist-info/METADATA
llm_lens-0.0.0.3.dist-info/WHEEL
llm_lens-0.0.0.3.dist-info/top_level.txt
llm_lens-0.0.0.3.dist-info/RECORD
