Metadata-Version: 2.1
Name: llm-lens
Version: 0.0.0.3
Summary: llm-lens is a Python package for CV as NLP, where you can run very descriptive image modules on images, and then pass those descriptions to a Large Language Model (LLM) to reason about those images.
Home-page: https://github.com/ContextualAI/lens
Author: The Contextual AI Tech Team
Author-email: tech@contextual.ai
Classifier: Programming Language :: Python :: 3.9
Classifier: Topic :: Scientific/Engineering :: Artificial Intelligence
Requires-Python: >=3.9
Requires-Dist: torch
Requires-Dist: transformers
Requires-Dist: evaluate
Requires-Dist: datasets
Requires-Dist: tqdm
Requires-Dist: accelerate
Requires-Dist: bitsandbytes
Requires-Dist: ftfy
Requires-Dist: regex
Requires-Dist: omegaconf
Requires-Dist: openai
Requires-Dist: opencv-python
Requires-Dist: nltk
Requires-Dist: scikit-learn
Requires-Dist: open-clip-torch
Requires-Dist: wandb
Requires-Dist: fairscale
Requires-Dist: huggingface-hub
